vb_downloader/__init__.py
vb_downloader/downloader.py
vb_downloader/gui.py
vb_downloader/wrapper.py
vb_downloader-1.0.0.data/scripts/vb-downloader.bat
vb_downloader-1.0.0.dist-info/LICENSE
vb_downloader-1.0.0.dist-info/METADATA
vb_downloader-1.0.0.dist-info/WHEEL
vb_downloader-1.0.0.dist-info/entry_points.txt
vb_downloader-1.0.0.dist-info/top_level.txt
vb_downloader-1.0.0.dist-info/RECORD
